gblninja/__init__.py
gblninja/gbl.py
gbl_ninja-1.0.0.dist-info/METADATA
gbl_ninja-1.0.0.dist-info/WHEEL
gbl_ninja-1.0.0.dist-info/top_level.txt
gbl_ninja-1.0.0.dist-info/RECORD
