Metadata-Version: 2.4
Name: gbl-ninja
Version: 1.0.0
Summary: Python library for parsing and creating GBL (Gecko Bootloader) files
Author-email: GBL Ninja <contact@gblninja.com>
License: MIT
Project-URL: Homepage, https://github.com/Onix-Systems/GBL-NINJA-SDK-Multiplatform
Project-URL: Repository, https://github.com/Onix-Systems/GBL-NINJA-SDK-Multiplatform
Project-URL: Documentation, https://github.com/Onix-Systems/GBL-NINJA-SDK-Multiplatform#readme
Project-URL: Issues, https://github.com/Onix-Systems/GBL-NINJA-SDK-Multiplatform/issues
Keywords: gbl,gecko,bootloader,silicon-labs,firmware
Classifier: Development Status :: 4 - Beta
Classifier: Intended Audience :: Developers
Classifier: License :: OSI Approved :: MIT License
Classifier: Programming Language :: Python :: 3
Classifier: Programming Language :: Python :: 3.6
Classifier: Programming Language :: Python :: 3.7
Classifier: Programming Language :: Python :: 3.8
Classifier: Programming Language :: Python :: 3.9
Classifier: Programming Language :: Python :: 3.10
Classifier: Programming Language :: Python :: 3.11
Classifier: Programming Language :: Python :: 3.12
Classifier: Topic :: Software Development :: Libraries :: Python Modules
Classifier: Topic :: System :: Hardware
Classifier: Topic :: Utilities
Requires-Python: >=3.6
